{"errors":[],"warnings":[],"namedChunkGroups":{"app":{"chunks":[7,0,2],"assets":["webpack-runtime-9b0ebad11ce8f665e27f.js","webpack-runtime-9b0ebad11ce8f665e27f.js.map","styles.6d79c8a5d102de2894fb.css","styles-bda35acd711f683427d9.js","styles-bda35acd711f683427d9.js.map","app-9864a0c1ef937c86cea8.js","app-9864a0c1ef937c86cea8.js.map"],"children":{},"childAssets":{}},"component---src-pages-404-js":{"chunks":[0,1,3],"assets":["styles.6d79c8a5d102de2894fb.css","styles-bda35acd711f683427d9.js","styles-bda35acd711f683427d9.js.map","1-a1f12bb347893474598c.js","1-a1f12bb347893474598c.js.map","component---src-pages-404-js-6f9cc84e599661351d96.js","component---src-pages-404-js-6f9cc84e599661351d96.js.map"],"children":{},"childAssets":{}},"component---src-pages-index-js":{"chunks":[0,1,4],"assets":["styles.6d79c8a5d102de2894fb.css","styles-bda35acd711f683427d9.js","styles-bda35acd711f683427d9.js.map","1-a1f12bb347893474598c.js","1-a1f12bb347893474598c.js.map","component---src-pages-index-js-b3ed1f15aac9a89fda22.js","component---src-pages-index-js-b3ed1f15aac9a89fda22.js.map"],"children":{},"childAssets":{}},"component---src-pages-page-2-js":{"chunks":[0,1,5],"assets":["styles.6d79c8a5d102de2894fb.css","styles-bda35acd711f683427d9.js","styles-bda35acd711f683427d9.js.map","1-a1f12bb347893474598c.js","1-a1f12bb347893474598c.js.map","component---src-pages-page-2-js-75066cf754e166fa2c16.js","component---src-pages-page-2-js-75066cf754e166fa2c16.js.map"],"children":{},"childAssets":{}},"pages-manifest":{"chunks":[6],"assets":["pages-manifest-59d6f11a9a4a7f59c89a.js","pages-manifest-59d6f11a9a4a7f59c89a.js.map"],"children":{},"childAssets":{}}},"assetsByChunkName":{"app":["webpack-runtime-9b0ebad11ce8f665e27f.js","styles.6d79c8a5d102de2894fb.css","styles-bda35acd711f683427d9.js","app-9864a0c1ef937c86cea8.js"],"component---src-pages-404-js":["styles.6d79c8a5d102de2894fb.css","styles-bda35acd711f683427d9.js","1-a1f12bb347893474598c.js","component---src-pages-404-js-6f9cc84e599661351d96.js"],"component---src-pages-index-js":["styles.6d79c8a5d102de2894fb.css","styles-bda35acd711f683427d9.js","1-a1f12bb347893474598c.js","component---src-pages-index-js-b3ed1f15aac9a89fda22.js"],"component---src-pages-page-2-js":["styles.6d79c8a5d102de2894fb.css","styles-bda35acd711f683427d9.js","1-a1f12bb347893474598c.js","component---src-pages-page-2-js-75066cf754e166fa2c16.js"],"pages-manifest":["pages-manifest-59d6f11a9a4a7f59c89a.js"]}}